pypi_mcp_test_khoms/__init__.py
pypi_mcp_test_khoms/pypi_mcp_test_khoms.py
pypi_mcp_test_khoms-1.0.0.dist-info/METADATA
pypi_mcp_test_khoms-1.0.0.dist-info/WHEEL
pypi_mcp_test_khoms-1.0.0.dist-info/entry_points.txt
pypi_mcp_test_khoms-1.0.0.dist-info/RECORD
