Metadata-Version: 2.4
Name: pypi-mcp-test-khoms
Version: 1.0.0
Summary: A simple mcp test server
Requires-Python: >=3.12
Requires-Dist: build>=1.2.2.post1
Requires-Dist: mcp[cli]>=1.12.2
Requires-Dist: twine>=6.1.0
